Metadata-Version: 2.1
Name: django-bitfield-ivc
Version: 2.1.0.post1
Summary: BitField in Django
Home-page: https://github.com/disqus/django-bitfield
Author: Disqus
Author-email: opensource@disqus.com
License: UNKNOWN
Platform: UNKNOWN
Classifier: Framework :: Django
Classifier: Intended Audience :: Developers
Classifier: Intended Audience :: System Administrators
Classifier: Operating System :: OS Independent
Classifier: Topic :: Software Development
Classifier: Programming Language :: Python
Classifier: Programming Language :: Python :: 2
Classifier: Programming Language :: Python :: 2.7
Classifier: Programming Language :: Python :: 3
Classifier: Programming Language :: Python :: 3.4
Classifier: Programming Language :: Python :: 3.5
Classifier: Programming Language :: Python :: 3.6
Classifier: Programming Language :: Python :: 3.7
Classifier: Programming Language :: Python :: 3.8
Classifier: Programming Language :: Python :: 3.9
Requires-Dist: Django (>=4.0.1)
Requires-Dist: six
Provides-Extra: tests
Requires-Dist: flake8 ; extra == 'tests'
Requires-Dist: mysqlclient ; extra == 'tests'
Requires-Dist: psycopg2 (>=2.3) ; extra == 'tests'
Requires-Dist: pytest-django ; extra == 'tests'
